{
  "_class": "shapeGroup",
  "booleanOperation": -1,
  "clippingMaskMode": 0,
  "do_objectID": "C5B6BF8B-3174-4779-890F-B72D5516DD88",
  "exportOptions": {
    "_class": "exportOptions",
    "do_objectID": "171CBC88-F2E9-4BCC-B539-671279E6043C",
    "exportFormats": [
    ],
    "includedLayerIds": [
    ],
    "layerOptions": 0,
    "shouldTrim": false
  },
  "frame": {
    "_class": "rect",
    "constrainProportions": false,
    "do_objectID": "5147D46C-53B0-4431-92E9-0C01E9B6A28B",
    "height": 52.84011517070761,
    "width": 53.20934508933738,
    "x": 1080.390546452263,
    "y": 230.3803191489365
  },
  "hasClickThrough": false,
  "hasClippingMask": false,
  "isFixedToViewport": false,
  "isFlippedHorizontal": true,
  "isFlippedVertical": false,
  "isLocked": false,
  "isVisible": true,
  "layerListExpandedType": 0,
  "layers": [
    {
      "class": "shapePath",
      "id": "C4E237FE-6CD8-460B-9F5D-9C71F9E6EECB"
    },
    {
      "class": "shapePath",
      "id": "C64B61B8-55FD-4C44-AF2F-2BAC04538636"
    }
  ],
  "name": "Combined Shape Copy 10",
  "nameIsFixed": false,
  "resizingConstraint": 63,
  "resizingType": 0,
  "rotation": 0,
  "shouldBreakMaskChain": false,
  "style": {
    "_class": "style",
    "do_objectID": "ADA152CC-344C-40A3-A505-032A389574BA",
    "endMarkerType": 0,
    "fills": [
      {
        "_class": "fill",
        "color": {
          "_class": "color",
          "alpha": 1,
          "blue": 0.5873479843139648,
          "green": 0.3970861732959747,
          "red": 0.4020573198795319
        },
        "fillType": 0,
        "isEnabled": true,
        "noiseIndex": 0,
        "noiseIntensity": 0,
        "patternFillType": 1,
        "patternTileScale": 1
      }
    ],
    "miterLimit": 10,
    "startMarkerType": 0,
    "windingRule": 0
  },
  "userInfo": {
    "com.animaapp.stc-sketch-plugin": {
      "kModelPropertiesKey": {
      }
    }
  },
  "windingRule": 0
}