{
  "_class": "shapeGroup",
  "booleanOperation": 0,
  "clippingMaskMode": 0,
  "do_objectID": "800E0D7D-BD4F-4A2A-A364-9DAC63CB859C",
  "exportOptions": {
    "_class": "exportOptions",
    "do_objectID": "3B971377-A813-4AC7-B1CA-D0EA7224F553",
    "exportFormats": [
    ],
    "includedLayerIds": [
    ],
    "layerOptions": 0,
    "shouldTrim": false
  },
  "frame": {
    "_class": "rect",
    "constrainProportions": false,
    "do_objectID": "401341CD-4411-4DCD-AEA7-7FBE0E1002E0",
    "height": 134,
    "width": 138,
    "x": 340,
    "y": 4
  },
  "hasClickThrough": false,
  "hasClippingMask": false,
  "isFixedToViewport": false,
  "isFlippedHorizontal": false,
  "isFlippedVertical": false,
  "isLocked": false,
  "isVisible": true,
  "layerListExpandedType": 2,
  "layers": [
    {
      "class": "shapePath",
      "id": "042133AB-9E32-4045-9CCE-87E682D708A1"
    },
    {
      "class": "shapePath",
      "id": "B7549F41-A720-43FE-86F8-25F306F0B93E"
    }
  ],
  "name": "Combined Shape Copy 67",
  "nameIsFixed": false,
  "resizingConstraint": 63,
  "resizingType": 0,
  "rotation": 0,
  "shouldBreakMaskChain": false,
  "style": {
    "_class": "style",
    "blur": {
      "_class": "blur",
      "center": "{0.5, 0.5}",
      "do_objectID": "0E9BACC0-39AA-401F-BBB1-2E915EED06EE",
      "isEnabled": false,
      "motionAngle": 0,
      "radius": 7.065921327020627,
      "saturation": 1,
      "type": 0
    },
    "borders": [
      {
        "_class": "border",
        "color": {
          "_class": "color",
          "alpha": 1,
          "blue": 0.5920650959014893,
          "green": 0.5919613242149353,
          "red": 0.5920420289039612
        },
        "fillType": 0,
        "isEnabled": false,
        "position": 0,
        "thickness": 1.177653554503437
      }
    ],
    "do_objectID": "F51E3C93-0DE1-4843-B577-ECB686788ABB",
    "endMarkerType": 0,
    "fills": [
      {
        "_class": "fill",
        "color": {
          "_class": "color",
          "alpha": 1,
          "blue": 1,
          "green": 0.9999368786811829,
          "red": 1
        },
        "fillType": 0,
        "isEnabled": true,
        "noiseIndex": 0,
        "noiseIntensity": 0,
        "patternFillType": 1,
        "patternTileScale": 1
      }
    ],
    "miterLimit": 10,
    "startMarkerType": 0,
    "windingRule": 1
  },
  "userInfo": {
    "com.animaapp.stc-sketch-plugin": {
      "kModelPropertiesKey": {
      }
    }
  },
  "windingRule": 1
}