{
  "_class": "shapePath",
  "booleanOperation": -1,
  "clippingMaskMode": 0,
  "do_objectID": "873F2696-F366-4825-8838-180769515A4F",
  "edited": true,
  "exportOptions": {
    "_class": "exportOptions",
    "do_objectID": "5AC85726-18EC-426C-9544-0DCBCCA61E8D",
    "exportFormats": [
    ],
    "includedLayerIds": [
    ],
    "layerOptions": 0,
    "shouldTrim": false
  },
  "frame": {
    "_class": "rect",
    "constrainProportions": false,
    "do_objectID": "9397B362-4CC0-44BE-BBE6-E85570036D14",
    "height": 20.78227809129814,
    "width": 24,
    "x": 0,
    "y": 5.684341886080801e-14
  },
  "hasClippingMask": false,
  "isClosed": true,
  "isFixedToViewport": false,
  "isFlippedHorizontal": false,
  "isFlippedVertical": false,
  "isLocked": false,
  "isVisible": true,
  "layerListExpandedType": 0,
  "name": "Path",
  "nameIsFixed": false,
  "pointRadiusBehaviour": 0,
  "points": [
    {
      "_class": "curvePoint",
      "cornerRadius": 0,
      "curveFrom": "{0.936726068172407, -0.010186246872862884}",
      "curveMode": 4,
      "curveTo": "{0.97288260064531729, 0.03055874061858865}",
      "hasCurveFrom": true,
      "hasCurveTo": false,
      "point": "{0.97288260064531729, 0.03055874061858865}"
    },
    {
      "_class": "curvePoint",
      "cornerRadius": 0,
      "curveFrom": "{0.84194407768810686, 0.03055874061858865}",
      "curveMode": 4,
      "curveTo": "{0.87810061016101659, -0.010186246872862884}",
      "hasCurveFrom": false,
      "hasCurveTo": true,
      "point": "{0.84194407768810686, 0.03055874061858865}"
    },
    {
      "_class": "curvePoint",
      "cornerRadius": 0,
      "curveFrom": "{0.23940812037594039, 0.63399129179449798}",
      "curveMode": 4,
      "curveTo": "{0.30512738380768573, 0.63570386569956772}",
      "hasCurveFrom": true,
      "hasCurveTo": false,
      "point": "{0.30512738380768573, 0.63570386569956772}"
    },
    {
      "_class": "curvePoint",
      "cornerRadius": 0,
      "curveFrom": "{0.079063117680606879, 0.88520447649440559}",
      "curveMode": 4,
      "curveTo": "{0.14837615918874375, 0.66057186594609651}",
      "hasCurveFrom": true,
      "hasCurveTo": true,
      "point": "{0.10909460230158043, 0.80749643555187267}"
    },
    {
      "_class": "curvePoint",
      "cornerRadius": 0,
      "curveFrom": "{0.16415753248072243, 1.0891791643128135}",
      "curveMode": 4,
      "curveTo": "{0, 0.88127982796195781}",
      "hasCurveFrom": true,
      "hasCurveTo": true,
      "point": "{0, 0.88127982796195781}"
    },
    {
      "_class": "curvePoint",
      "cornerRadius": 0,
      "curveFrom": "{0.44062844240970639, 0.87539285516328202}",
      "curveMode": 2,
      "curveTo": "{0.35762779396714028, 0.97136835109322295}",
      "hasCurveFrom": true,
      "hasCurveTo": true,
      "point": "{0.40178438894053842, 0.92027656292531002}"
    },
    {
      "_class": "curvePoint",
      "cornerRadius": 0,
      "curveFrom": "{0.44206595364026263, 0.77649171214550183}",
      "curveMode": 4,
      "curveTo": "{0.44622223611121931, 0.82044777570895611}",
      "hasCurveFrom": false,
      "hasCurveTo": true,
      "point": "{0.44206595364026263, 0.77649171214550183}"
    },
    {
      "_class": "curvePoint",
      "cornerRadius": 0,
      "curveFrom": "{1.0090391331182276, 0.13738053794730737}",
      "curveMode": 4,
      "curveTo": "{0.97288260064531729, 0.17816120406178035}",
      "hasCurveFrom": true,
      "hasCurveTo": false,
      "point": "{0.97288260064531729, 0.17816120406178035}"
    },
    {
      "_class": "curvePoint",
      "cornerRadius": 0,
      "curveFrom": "{0.97288260064531729, 0.03055874061858865}",
      "curveMode": 4,
      "curveTo": "{1.0090391331182276, 0.071303728110040182}",
      "hasCurveFrom": false,
      "hasCurveTo": true,
      "point": "{0.97288260064531729, 0.03055874061858865}"
    }
  ],
  "resizingConstraint": 63,
  "resizingType": 0,
  "rotation": 0,
  "shouldBreakMaskChain": false,
  "style": {
    "_class": "style",
    "blur": {
      "_class": "blur",
      "center": "{0.5, 0.5}",
      "do_objectID": "785D7362-26BB-43C0-AD40-6E38F3A34F30",
      "isEnabled": false,
      "motionAngle": 0,
      "radius": 9.999999999999998,
      "saturation": 1,
      "type": 0
    },
    "do_objectID": "C3B28AF7-7A2E-4E15-865D-D6C6BA617D4A",
    "endMarkerType": 0,
    "fills": [
      {
        "_class": "fill",
        "color": {
          "_class": "color",
          "alpha": 1,
          "blue": 0,
          "green": 0,
          "red": 0
        },
        "fillType": 0,
        "isEnabled": true,
        "noiseIndex": 0,
        "noiseIntensity": 0,
        "patternFillType": 0,
        "patternTileScale": 1
      }
    ],
    "miterLimit": 10,
    "startMarkerType": 0,
    "windingRule": 1
  }
}