{
  "_class": "shapeGroup",
  "booleanOperation": 0,
  "clippingMaskMode": 0,
  "do_objectID": "38D651D2-4168-4EE6-B86A-01553DE5B758",
  "exportOptions": {
    "_class": "exportOptions",
    "do_objectID": "FE9BD3F0-4200-42EF-9E87-7D9636BC25B4",
    "exportFormats": [
    ],
    "includedLayerIds": [
    ],
    "layerOptions": 0,
    "shouldTrim": false
  },
  "frame": {
    "_class": "rect",
    "constrainProportions": true,
    "do_objectID": "301EE5AB-8BFA-43F7-96DA-6980FF652724",
    "height": 86.10215584864861,
    "width": 86.84978672432432,
    "x": 188.9241880216218,
    "y": 168.5788283675674
  },
  "hasClickThrough": false,
  "hasClippingMask": false,
  "isFixedToViewport": false,
  "isFlippedHorizontal": false,
  "isFlippedVertical": false,
  "isLocked": false,
  "isVisible": true,
  "layerListExpandedType": 2,
  "layers": [
    {
      "class": "oval",
      "id": "9EA85B59-14E8-46ED-BBE2-1CF579C704FC"
    },
    {
      "class": "oval",
      "id": "9A0C2879-3913-4E31-ABD2-0BF2510A8BE8"
    }
  ],
  "name": "Combined Shape Copy 23",
  "nameIsFixed": false,
  "resizingConstraint": 63,
  "resizingType": 0,
  "rotation": 0,
  "shouldBreakMaskChain": false,
  "style": {
    "_class": "style",
    "blur": {
      "_class": "blur",
      "center": "{0.5, 0.5}",
      "do_objectID": "DDD3DD3F-8564-4017-9C03-2CA446EFD635",
      "isEnabled": false,
      "motionAngle": 0,
      "radius": 1.424489739527358,
      "saturation": 1,
      "type": 0
    },
    "borders": [
      {
        "_class": "border",
        "color": {
          "_class": "color",
          "alpha": 1,
          "blue": 0.5920650959014893,
          "green": 0.5919613242149353,
          "red": 0.5920420289039612
        },
        "fillType": 0,
        "isEnabled": false,
        "position": 0,
        "thickness": 1.68
      }
    ],
    "do_objectID": "78C62D89-E4F5-4CE9-887C-80B85C735841",
    "endMarkerType": 0,
    "fills": [
      {
        "_class": "fill",
        "color": {
          "_class": "color",
          "alpha": 1,
          "blue": 1,
          "green": 0.9999368786811829,
          "red": 1
        },
        "fillType": 0,
        "isEnabled": true,
        "noiseIndex": 0,
        "noiseIntensity": 0,
        "patternFillType": 1,
        "patternTileScale": 1
      }
    ],
    "miterLimit": 10,
    "startMarkerType": 0,
    "windingRule": 1
  },
  "userInfo": {
    "com.animaapp.stc-sketch-plugin": {
      "kModelPropertiesKey": {
        "constraints": {
          "aspectRatio": {
            "constant": 122.5046,
            "enabled": 1,
            "modelID": "constraint_83f9c117-c19c-44d8-8c23-f756f64ea10a",
            "model_class": "ADModelConstraint",
            "model_version": 0.1,
            "multiplier": 123.3613
          },
          "automatic": 1,
          "modelID": "viewConstraints_7ae20be6-faad-4661-a667-0d87a985695f",
          "model_class": "ADModelViewConstraints",
          "model_version": 0.1,
          "scaleFactor": 1
        }
      }
    }
  },
  "windingRule": 1
}