{
  "_class": "group",
  "booleanOperation": -1,
  "clippingMaskMode": 0,
  "do_objectID": "A6EFB3C6-4375-4F63-96BF-CA180B1889E3",
  "exportOptions": {
    "_class": "exportOptions",
    "do_objectID": "8E00365B-F66F-42C1-81C7-630244012746",
    "exportFormats": [
    ],
    "includedLayerIds": [
    ],
    "layerOptions": 0,
    "shouldTrim": false
  },
  "frame": {
    "_class": "rect",
    "constrainProportions": false,
    "do_objectID": "0DA304FF-24EE-400A-8F48-A34CAED7377B",
    "height": 24,
    "width": 18,
    "x": 0,
    "y": 0
  },
  "hasClickThrough": false,
  "hasClippingMask": false,
  "isFixedToViewport": false,
  "isFlippedHorizontal": false,
  "isFlippedVertical": false,
  "isLocked": false,
  "isVisible": true,
  "layerListExpandedType": 0,
  "layers": [
    {
      "class": "shapeGroup",
      "id": "F878F0E6-524E-45FD-97B0-25EC990E11C9"
    }
  ],
  "name": "0: Icons / Dark / Location",
  "nameIsFixed": false,
  "resizingConstraint": 63,
  "resizingType": 0,
  "rotation": 0,
  "sharedStyleID": "8B8458CB-D9EB-4F9F-8B40-938357A63167",
  "shouldBreakMaskChain": false,
  "style": {
    "_class": "style",
    "do_objectID": "F2926808-080E-434F-BB4E-72EE517A86DA",
    "endMarkerType": 0,
    "fills": [
      {
        "_class": "fill",
        "color": {
          "_class": "color",
          "alpha": 1,
          "blue": 0.8235294117647058,
          "green": 0.2705882352941176,
          "red": 0.3137254901960782
        },
        "fillType": 0,
        "isEnabled": true,
        "noiseIndex": 0,
        "noiseIntensity": 0,
        "patternFillType": 0,
        "patternTileScale": 1
      }
    ],
    "miterLimit": 10,
    "startMarkerType": 0,
    "windingRule": 1
  },
  "userInfo": {
    "com.animaapp.stc-sketch-plugin": {
      "kModelPropertiesKey": {
      }
    }
  }
}