{
  "_class": "shapeGroup",
  "booleanOperation": -1,
  "clippingMaskMode": 0,
  "do_objectID": "10A1DF86-E20D-494E-96B0-872E0A15A2DF",
  "exportOptions": {
    "_class": "exportOptions",
    "do_objectID": "37310143-0832-4272-B27B-FCCFE5038982",
    "exportFormats": [
    ],
    "includedLayerIds": [
    ],
    "layerOptions": 0,
    "shouldTrim": false
  },
  "frame": {
    "_class": "rect",
    "constrainProportions": false,
    "do_objectID": "B8EEEA93-6EDF-4E89-9FC5-8A4D027B9D5F",
    "height": 250.5932596409911,
    "width": 222.0600904419248,
    "x": 380.559507678906,
    "y": 196.8297872340429
  },
  "hasClickThrough": false,
  "hasClippingMask": false,
  "isFixedToViewport": false,
  "isFlippedHorizontal": false,
  "isFlippedVertical": false,
  "isLocked": false,
  "isVisible": true,
  "layerListExpandedType": 0,
  "layers": [
    {
      "class": "shapePath",
      "id": "EB46C927-CA2E-4E1B-A628-2947909EBA60"
    },
    {
      "class": "shapePath",
      "id": "609D2C67-23BF-4E98-9F35-C2D7A50E02AF"
    },
    {
      "class": "shapePath",
      "id": "CB7E10EE-91BC-4F0C-8EE1-DE331C3D429C"
    },
    {
      "class": "shapePath",
      "id": "961493E9-C17E-4F3D-B10A-A75ECD42A51D"
    },
    {
      "class": "shapePath",
      "id": "2E34A4B9-E075-49F9-8B9A-772B38A003EA"
    },
    {
      "class": "shapePath",
      "id": "F1224A26-25CE-4938-9F2B-CD28B225ED83"
    }
  ],
  "name": "Combined Shape Copy 4",
  "nameIsFixed": false,
  "resizingConstraint": 63,
  "resizingType": 0,
  "rotation": 0,
  "shouldBreakMaskChain": false,
  "style": {
    "_class": "style",
    "do_objectID": "4E81C9C2-7E6C-49D2-A9F4-8EDBA3B5897D",
    "endMarkerType": 0,
    "fills": [
      {
        "_class": "fill",
        "color": {
          "_class": "color",
          "alpha": 1,
          "blue": 0.5873479843139648,
          "green": 0.3970861732959747,
          "red": 0.4020573198795319
        },
        "fillType": 0,
        "isEnabled": true,
        "noiseIndex": 0,
        "noiseIntensity": 0,
        "patternFillType": 1,
        "patternTileScale": 1
      }
    ],
    "miterLimit": 10,
    "startMarkerType": 0,
    "windingRule": 0
  },
  "userInfo": {
    "com.animaapp.stc-sketch-plugin": {
      "kModelPropertiesKey": {
      }
    }
  },
  "windingRule": 0
}