{
  "_class": "shapePath",
  "booleanOperation": -1,
  "clippingMaskMode": 0,
  "do_objectID": "881E82F1-198D-4950-99AA-D1AEBE11B19A",
  "edited": true,
  "exportOptions": {
    "_class": "exportOptions",
    "do_objectID": "A10E6FF0-408C-4B18-B235-2F761E07F38F",
    "exportFormats": [
    ],
    "includedLayerIds": [
    ],
    "layerOptions": 0,
    "shouldTrim": false
  },
  "frame": {
    "_class": "rect",
    "constrainProportions": false,
    "do_objectID": "7B2071A0-74B3-4C41-93D7-09BDFF513840",
    "height": 3,
    "width": 4,
    "x": 0,
    "y": 199
  },
  "hasClippingMask": false,
  "isClosed": false,
  "isFixedToViewport": false,
  "isFlippedHorizontal": false,
  "isFlippedVertical": false,
  "isLocked": false,
  "isVisible": true,
  "layerListExpandedType": 1,
  "name": "Fill 33 Copy 5",
  "nameIsFixed": false,
  "pointRadiusBehaviour": 1,
  "points": [
    {
      "_class": "curvePoint",
      "cornerRadius": 0,
      "curveFrom": "{0.80165264071879405, 0.014357139378470031}",
      "curveMode": 4,
      "curveTo": "{0.52856667502424515, 0.001003351812337894}",
      "hasCurveFrom": true,
      "hasCurveTo": false,
      "point": "{0.52856667502424515, 0.001003351812337894}"
    },
    {
      "_class": "curvePoint",
      "cornerRadius": 0,
      "curveFrom": "{0.99943956029521708, 0.52695801737438908}",
      "curveMode": 4,
      "curveTo": "{1.0123189571117301, 0.24973121615389121}",
      "hasCurveFrom": false,
      "hasCurveTo": true,
      "point": "{0.99943956029521708, 0.52695801737438908}"
    },
    {
      "_class": "curvePoint",
      "cornerRadius": 0,
      "curveFrom": "{0.98410185537264627, 0.80391340014841806}",
      "curveMode": 4,
      "curveTo": "{0.99943956029521708, 0.52815225853883951}",
      "hasCurveFrom": true,
      "hasCurveTo": false,
      "point": "{0.99943956029521708, 0.52815225853883951}"
    },
    {
      "_class": "curvePoint",
      "cornerRadius": 0,
      "curveFrom": "{0.19835176660416401, 0.98608946141647835}",
      "curveMode": 2,
      "curveTo": "{0.74708888906045012, 1.0144255472275412}",
      "hasCurveFrom": true,
      "hasCurveTo": true,
      "point": "{0.471437732298713, 0.99922611422543972}"
    },
    {
      "_class": "curvePoint",
      "cornerRadius": 0,
      "curveFrom": "{0.00056484702774105538, 0.47310859759550961}",
      "curveMode": 4,
      "curveTo": "{-0.012367991269338789, 0.75071538464105725}",
      "hasCurveFrom": false,
      "hasCurveTo": true,
      "point": "{0.00056484702774105538, 0.47310859759550961}"
    },
    {
      "_class": "curvePoint",
      "cornerRadius": 0,
      "curveFrom": "{0.019055599303732192, 0.19387329987116361}",
      "curveMode": 4,
      "curveTo": "{0.00056484702774105538, 0.47164293798459328}",
      "hasCurveFrom": true,
      "hasCurveTo": false,
      "point": "{0.00056484702774105538, 0.47164293798459328}"
    },
    {
      "_class": "curvePoint",
      "cornerRadius": 0,
      "curveFrom": "{0.52856667502424515, 0.001003351812337894}",
      "curveMode": 4,
      "curveTo": "{0.25494629452403211, -0.016367428761493504}",
      "hasCurveFrom": false,
      "hasCurveTo": true,
      "point": "{0.52856667502424515, 0.001003351812337894}"
    }
  ],
  "resizingConstraint": 63,
  "resizingType": 0,
  "rotation": 0,
  "shouldBreakMaskChain": false,
  "style": {
    "_class": "style",
    "do_objectID": "A0A43293-65AC-4ECB-A5F3-6337D8FA65C1",
    "endMarkerType": 0,
    "fills": [
      {
        "_class": "fill",
        "color": {
          "_class": "color",
          "alpha": 1,
          "blue": 1,
          "green": 0.9999368786811829,
          "red": 1
        },
        "fillType": 0,
        "isEnabled": true,
        "noiseIndex": 0,
        "noiseIntensity": 0,
        "patternFillType": 1,
        "patternTileScale": 1
      }
    ],
    "miterLimit": 10,
    "startMarkerType": 0,
    "windingRule": 1
  },
  "userInfo": {
    "com.animaapp.stc-sketch-plugin": {
      "kModelPropertiesKey": {
      }
    }
  }
}