{
  "_class": "group",
  "booleanOperation": -1,
  "clippingMaskMode": 0,
  "do_objectID": "DD409CC1-1B23-4DE4-9B20-D09A38420874",
  "exportOptions": {
    "_class": "exportOptions",
    "do_objectID": "5C41544B-8E9A-49B2-909F-2F71FAFEDE42",
    "exportFormats": [
    ],
    "includedLayerIds": [
    ],
    "layerOptions": 0,
    "shouldTrim": false
  },
  "frame": {
    "_class": "rect",
    "constrainProportions": false,
    "do_objectID": "62B5DE49-602C-475A-A8CA-87B53B165F47",
    "height": 24,
    "width": 24,
    "x": 0,
    "y": 0
  },
  "hasClickThrough": false,
  "hasClippingMask": false,
  "isFixedToViewport": false,
  "isFlippedHorizontal": false,
  "isFlippedVertical": false,
  "isLocked": false,
  "isVisible": true,
  "layerListExpandedType": 0,
  "layers": [
    {
      "class": "shapeGroup",
      "id": "F8648FB7-7BB3-41DE-A80F-6E47DA46867B"
    }
  ],
  "name": "0: Icons / Dark / Pin",
  "nameIsFixed": false,
  "resizingConstraint": 63,
  "resizingType": 0,
  "rotation": 0,
  "shouldBreakMaskChain": false,
  "style": {
    "_class": "style",
    "blur": {
      "_class": "blur",
      "center": "{0.5, 0.5}",
      "do_objectID": "31741AD4-0D32-420E-9720-6175AE912C63",
      "isEnabled": false,
      "motionAngle": 0,
      "radius": 9.999999999999998,
      "saturation": 1,
      "type": 0
    },
    "do_objectID": "C8B477EB-6D99-42F9-B0CA-155E1D8B4E04",
    "endMarkerType": 0,
    "miterLimit": 10,
    "startMarkerType": 0,
    "windingRule": 1
  },
  "userInfo": {
    "com.animaapp.stc-sketch-plugin": {
      "kModelPropertiesKey": {
      }
    }
  }
}