{
  "_class": "shapeGroup",
  "booleanOperation": 0,
  "clippingMaskMode": 0,
  "do_objectID": "D36C5394-B1A8-4C48-A720-F5CBC2FC5CB7",
  "exportOptions": {
    "_class": "exportOptions",
    "do_objectID": "426E2952-FDE8-40AD-861A-2202BBE38B38",
    "exportFormats": [
    ],
    "includedLayerIds": [
    ],
    "layerOptions": 0,
    "shouldTrim": false
  },
  "frame": {
    "_class": "rect",
    "constrainProportions": false,
    "do_objectID": "7D0AB21D-7265-4CAD-8E53-683C448C7E8D",
    "height": 53.56521739130434,
    "width": 53.58222222222219,
    "x": 311.7511111111112,
    "y": 2.434782608695652
  },
  "hasClickThrough": false,
  "hasClippingMask": false,
  "isFixedToViewport": false,
  "isFlippedHorizontal": false,
  "isFlippedVertical": false,
  "isLocked": false,
  "isVisible": true,
  "layerListExpandedType": 2,
  "layers": [
    {
      "class": "shapePath",
      "id": "CDFC44F0-B5C0-4ADB-BA46-E627F02F2D4B"
    },
    {
      "class": "shapePath",
      "id": "A9CB3970-302F-43B5-9A18-A3678C65B198"
    }
  ],
  "name": "Combined Shape Copy 22",
  "nameIsFixed": false,
  "resizingConstraint": 63,
  "resizingType": 0,
  "rotation": 0,
  "shouldBreakMaskChain": false,
  "style": {
    "_class": "style",
    "blur": {
      "_class": "blur",
      "center": "{0.5, 0.5}",
      "do_objectID": "86F1EF3E-948B-46C4-9161-760853800BF2",
      "isEnabled": false,
      "motionAngle": 0,
      "radius": 3.918853177344,
      "saturation": 1,
      "type": 0
    },
    "borders": [
      {
        "_class": "border",
        "color": {
          "_class": "color",
          "alpha": 1,
          "blue": 0.5920650959014893,
          "green": 0.5919613242149353,
          "red": 0.5920420289039612
        },
        "fillType": 0,
        "isEnabled": false,
        "position": 0,
        "thickness": 0.5
      }
    ],
    "do_objectID": "B968481F-C6F6-421A-9118-81157DBB8F36",
    "endMarkerType": 0,
    "fills": [
      {
        "_class": "fill",
        "color": {
          "_class": "color",
          "alpha": 1,
          "blue": 1,
          "green": 1,
          "red": 1
        },
        "fillType": 0,
        "isEnabled": true,
        "noiseIndex": 0,
        "noiseIntensity": 0,
        "patternFillType": 1,
        "patternTileScale": 1
      }
    ],
    "miterLimit": 10,
    "startMarkerType": 0,
    "windingRule": 1
  },
  "userInfo": {
    "com.animaapp.stc-sketch-plugin": {
      "kModelPropertiesKey": {
      }
    }
  },
  "windingRule": 1
}