{
  "_class": "group",
  "booleanOperation": -1,
  "clippingMaskMode": 0,
  "do_objectID": "6B1F9236-115E-4EBE-A9ED-441F63A1CA4D",
  "exportOptions": {
    "_class": "exportOptions",
    "do_objectID": "1EA5CFCA-9A30-4CC9-8C20-0A6A842A53CF",
    "exportFormats": [
    ],
    "includedLayerIds": [
    ],
    "layerOptions": 0,
    "shouldTrim": false
  },
  "frame": {
    "_class": "rect",
    "constrainProportions": false,
    "do_objectID": "03748B12-B824-44E0-864F-5368BCDBBD35",
    "height": 24,
    "width": 24,
    "x": 0,
    "y": 0
  },
  "hasClickThrough": false,
  "hasClippingMask": false,
  "isFixedToViewport": false,
  "isFlippedHorizontal": false,
  "isFlippedVertical": false,
  "isLocked": false,
  "isVisible": true,
  "layerListExpandedType": 0,
  "layers": [
    {
      "class": "shapeGroup",
      "id": "D952171C-9AE6-46C0-B126-627175553D42"
    }
  ],
  "name": "0: Icons / Dark / Shrink",
  "nameIsFixed": false,
  "resizingConstraint": 63,
  "resizingType": 0,
  "rotation": 0,
  "sharedStyleID": "8B8458CB-D9EB-4F9F-8B40-938357A63167",
  "shouldBreakMaskChain": false,
  "style": {
    "_class": "style",
    "do_objectID": "67A7AC9E-6E19-4EA0-A0B1-C1B9FC46A637",
    "endMarkerType": 0,
    "fills": [
      {
        "_class": "fill",
        "color": {
          "_class": "color",
          "alpha": 1,
          "blue": 0.8235294117647058,
          "green": 0.2705882352941176,
          "red": 0.3137254901960782
        },
        "fillType": 0,
        "isEnabled": true,
        "noiseIndex": 0,
        "noiseIntensity": 0,
        "patternFillType": 0,
        "patternTileScale": 1
      }
    ],
    "miterLimit": 10,
    "startMarkerType": 0,
    "windingRule": 1
  },
  "userInfo": {
    "com.animaapp.stc-sketch-plugin": {
      "kModelPropertiesKey": {
      }
    }
  }
}