{
  "_class": "group",
  "booleanOperation": -1,
  "clippingMaskMode": 0,
  "do_objectID": "BB99B3D6-E1E5-4BEE-9F08-7CF6B7902968",
  "exportOptions": {
    "_class": "exportOptions",
    "exportFormats": [
    ],
    "includedLayerIds": [
    ],
    "layerOptions": 0,
    "shouldTrim": false
  },
  "frame": {
    "_class": "rect",
    "constrainProportions": false,
    "height": 69,
    "width": 136,
    "x": 80,
    "y": 0
  },
  "hasClickThrough": false,
  "hasClippingMask": false,
  "isFixedToViewport": false,
  "isFlippedHorizontal": false,
  "isFlippedVertical": false,
  "isLocked": false,
  "isVisible": true,
  "layerListExpandedType": 2,
  "layers": [
    {
      "class": "symbolInstance",
      "id": "48C451A1-03AD-46A4-A636-F6F6F9D2AA06"
    },
    {
      "class": "text",
      "id": "E4D8EA89-E9CA-4BC4-A57D-C86F1DBCC3E1"
    },
    {
      "class": "text",
      "id": "1D72E6C4-D523-4A27-8547-A8189BED296A"
    },
    {
      "class": "symbolInstance",
      "id": "4DC7DAA4-CE1B-4CFA-84A0-2F43FAEDBBE9"
    },
    {
      "class": "symbolInstance",
      "id": "ED6EA834-A3F0-4EBF-8B8A-1D49B8A9238C"
    }
  ],
  "name": "Stacked Group",
  "nameIsFixed": false,
  "resizingConstraint": 63,
  "resizingType": 0,
  "rotation": 0,
  "shouldBreakMaskChain": false,
  "style": {
    "_class": "style",
    "endMarkerType": 0,
    "miterLimit": 10,
    "startMarkerType": 0,
    "windingRule": 1
  },
  "userInfo": {
    "com.animaapp.stc-sketch-plugin": {
      "kModelPropertiesKey": {
        "align": 2,
        "isCollapsing": 1,
        "spacing": 0,
        "stackType": 0
      },
      "kViewTypeKey": "ADModelStackView"
    }
  }
}