{
  "_class": "group",
  "booleanOperation": 0,
  "clippingMaskMode": 0,
  "do_objectID": "1CA2AED8-A7FE-46E1-A141-B403C881CD4D",
  "exportOptions": {
    "_class": "exportOptions",
    "do_objectID": "7B137A7C-D85B-4F35-87DB-41707C4989AD",
    "exportFormats": [
    ],
    "includedLayerIds": [
    ],
    "layerOptions": 0,
    "shouldTrim": false
  },
  "frame": {
    "_class": "rect",
    "constrainProportions": false,
    "do_objectID": "A183D1DC-0BC2-4F2F-9780-42D5145B4B06",
    "height": 52.45901639344262,
    "width": 62.95081967213115,
    "x": 0.06801945054292922,
    "y": 0
  },
  "hasClickThrough": false,
  "hasClippingMask": false,
  "isFixedToViewport": false,
  "isFlippedHorizontal": false,
  "isFlippedVertical": false,
  "isLocked": false,
  "isVisible": true,
  "layerListExpandedType": 2,
  "layers": [
    {
      "class": "group",
      "id": "9C4D93DF-399F-4ADA-BC54-B76063D23372"
    }
  ],
  "name": "noun_116117_cc",
  "nameIsFixed": false,
  "resizingConstraint": 63,
  "resizingType": 0,
  "rotation": 0,
  "shouldBreakMaskChain": false,
  "style": {
    "_class": "style",
    "blur": {
      "_class": "blur",
      "center": "{0.5, 0.5}",
      "do_objectID": "E28C62E1-EA4D-4B6C-AAD2-011ED4F157F1",
      "isEnabled": false,
      "motionAngle": 0,
      "radius": 6.504960000000001,
      "saturation": 1,
      "type": 0
    },
    "do_objectID": "65A9C6F4-FB75-4F2C-A754-7D85473F2AFB",
    "endMarkerType": 0,
    "miterLimit": 10,
    "startMarkerType": 0,
    "windingRule": 1
  },
  "userInfo": {
    "com.animaapp.stc-sketch-plugin": {
      "kModelPropertiesKey": {
      }
    }
  }
}