{
  "_class": "shapePath",
  "booleanOperation": 0,
  "clippingMaskMode": 0,
  "do_objectID": "938A04E1-78FA-4244-984E-3D5BBB37D3C6",
  "edited": true,
  "exportOptions": {
    "_class": "exportOptions",
    "do_objectID": "F4B05260-F4B4-424B-80B6-37CD43A538E6",
    "exportFormats": [
    ],
    "includedLayerIds": [
    ],
    "layerOptions": 0,
    "shouldTrim": false
  },
  "frame": {
    "_class": "rect",
    "constrainProportions": false,
    "do_objectID": "5917E3B3-4C60-42E4-B19C-AC792900F60D",
    "height": 64.99999999999987,
    "width": 55.00000000000005,
    "x": 248,
    "y": 1
  },
  "hasClippingMask": false,
  "isClosed": true,
  "isFixedToViewport": false,
  "isFlippedHorizontal": false,
  "isFlippedVertical": false,
  "isLocked": false,
  "isVisible": true,
  "layerListExpandedType": 1,
  "name": "Path Copy 16",
  "nameIsFixed": false,
  "pointRadiusBehaviour": 1,
  "points": [
    {
      "_class": "curvePoint",
      "cornerRadius": 0,
      "curveFrom": "{0, 0.90156918687588894}",
      "curveMode": 4,
      "curveTo": "{0, 0.96433666191155376}",
      "hasCurveFrom": false,
      "hasCurveTo": true,
      "point": "{0, 0.90156918687588894}"
    },
    {
      "_class": "curvePoint",
      "cornerRadius": 0,
      "curveFrom": "{0, 0.061340941512128974}",
      "curveMode": 4,
      "curveTo": "{0, 0.11269614835948839}",
      "hasCurveFrom": true,
      "hasCurveTo": false,
      "point": "{0, 0.11269614835948839}"
    },
    {
      "_class": "curvePoint",
      "cornerRadius": 0,
      "curveFrom": "{0.161073825503356, 0.011412268188305468}",
      "curveMode": 3,
      "curveTo": "{0.013422818791942759, 0.011412268188305468}",
      "hasCurveFrom": true,
      "hasCurveTo": true,
      "point": "{0.10067114093959213, 0.011412268188305468}"
    },
    {
      "_class": "curvePoint",
      "cornerRadius": 0,
      "curveFrom": "{0.21979865771812165, 0.061340941512128974}",
      "curveMode": 4,
      "curveTo": "{0.17449664429529876, 0.024251069900146839}",
      "hasCurveFrom": false,
      "hasCurveTo": true,
      "point": "{0.21979865771812165, 0.061340941512128974}"
    },
    {
      "_class": "curvePoint",
      "cornerRadius": 0,
      "curveFrom": "{0.77516778523489804, 0.65192582025677737}",
      "curveMode": 1,
      "curveTo": "{0.77516778523489804, 0.65192582025677737}",
      "hasCurveFrom": false,
      "hasCurveTo": false,
      "point": "{0.77516778523489804, 0.65192582025677737}"
    },
    {
      "_class": "curvePoint",
      "cornerRadius": 0,
      "curveFrom": "{0.77516778523489804, 0.051355206847365491}",
      "curveMode": 4,
      "curveTo": "{0.77516778523489804, 0.098430813124111116}",
      "hasCurveFrom": true,
      "hasCurveTo": false,
      "point": "{0.77516778523489804, 0.098430813124111116}"
    },
    {
      "_class": "curvePoint",
      "cornerRadius": 0,
      "curveFrom": "{0.94127516778523435, 0}",
      "curveMode": 2,
      "curveTo": "{0.82382550335570304, 0}",
      "hasCurveFrom": true,
      "hasCurveTo": true,
      "point": "{0.88087248322147049, 0}"
    },
    {
      "_class": "curvePoint",
      "cornerRadius": 0,
      "curveFrom": "{1, 0.098430813124111116}",
      "curveMode": 4,
      "curveTo": "{1, 0.051355206847365491}",
      "hasCurveFrom": false,
      "hasCurveTo": true,
      "point": "{1, 0.098430813124111116}"
    },
    {
      "_class": "curvePoint",
      "cornerRadius": 0,
      "curveFrom": "{1, 0.96433666191155376}",
      "curveMode": 4,
      "curveTo": "{1, 0.90156918687588894}",
      "hasCurveFrom": true,
      "hasCurveTo": false,
      "point": "{1, 0.90156918687588894}"
    },
    {
      "_class": "curvePoint",
      "cornerRadius": 0,
      "curveFrom": "{0.85234899328858682, 1}",
      "curveMode": 4,
      "curveTo": "{0.95469798657717708, 0.98858773181170057}",
      "hasCurveFrom": true,
      "hasCurveTo": true,
      "point": "{0.91107382550335247, 1}"
    },
    {
      "_class": "curvePoint",
      "cornerRadius": 0,
      "curveFrom": "{0.77516778523489804, 0.95007132667617644}",
      "curveMode": 4,
      "curveTo": "{0.82382550335570304, 0.98858773181170057}",
      "hasCurveFrom": false,
      "hasCurveTo": true,
      "point": "{0.77516778523489804, 0.95007132667617644}"
    },
    {
      "_class": "curvePoint",
      "cornerRadius": 0,
      "curveFrom": "{0.21979865771812165, 0.35092724679030046}",
      "curveMode": 1,
      "curveTo": "{0.21979865771812165, 0.35092724679030046}",
      "hasCurveFrom": false,
      "hasCurveTo": false,
      "point": "{0.21979865771812165, 0.35092724679030046}"
    },
    {
      "_class": "curvePoint",
      "cornerRadius": 0,
      "curveFrom": "{0.21979865771812165, 0.96433666191155376}",
      "curveMode": 4,
      "curveTo": "{0.21979865771812165, 0.90156918687588894}",
      "hasCurveFrom": true,
      "hasCurveTo": false,
      "point": "{0.21979865771812165, 0.90156918687588894}"
    },
    {
      "_class": "curvePoint",
      "cornerRadius": 0,
      "curveFrom": "{0.053691275167785331, 1}",
      "curveMode": 2,
      "curveTo": "{0.17449664429529876, 1}",
      "hasCurveFrom": true,
      "hasCurveTo": true,
      "point": "{0.1140939597315349, 1}"
    }
  ],
  "resizingConstraint": 63,
  "resizingType": 0,
  "rotation": 0,
  "shouldBreakMaskChain": false,
  "style": {
    "_class": "style",
    "blur": {
      "_class": "blur",
      "center": "{0.5, 0.5}",
      "do_objectID": "76B6BB14-5BE3-45B5-A01A-3069E3CB9D77",
      "isEnabled": false,
      "motionAngle": 0,
      "radius": 7.065921327020627,
      "saturation": 1,
      "type": 0
    },
    "do_objectID": "8EEFEB3C-FDD9-4A97-B486-582CDE49B344",
    "endMarkerType": 0,
    "fills": [
      {
        "_class": "fill",
        "color": {
          "_class": "color",
          "alpha": 1,
          "blue": 0.2016327083110809,
          "green": 0.1796489953994751,
          "red": 0.1613196134567261
        },
        "fillType": 0,
        "isEnabled": true,
        "noiseIndex": 0,
        "noiseIntensity": 0,
        "patternFillType": 1,
        "patternTileScale": 1
      }
    ],
    "miterLimit": 10,
    "startMarkerType": 0,
    "textStyle": {
      "_class": "textStyle",
      "do_objectID": "85ECBD8C-559F-450F-B7B3-10F5ABC811BC",
      "encodedAttributes": {
        "MSAttributedStringColorAttribute": {
          "_class": "color",
          "alpha": 1,
          "blue": 0.8542995323,
          "green": 0.7468312181,
          "red": 0.111607708
        },
        "MSAttributedStringFontAttribute": {
          "_class": "fontDescriptor",
          "attributes": {
            "name": "Multicolore",
            "size": 106.7699966430664
          }
        },
        "kerning": 7.119999885559082,
        "paragraphStyle": {
          "_class": "paragraphStyle",
          "allowsDefaultTighteningForTruncation": 0
        }
      },
      "verticalAlignment": 0
    },
    "windingRule": 1
  },
  "userInfo": {
    "com.animaapp.stc-sketch-plugin": {
      "kModelPropertiesKey": {
      }
    }
  }
}