{
  "_class": "shapePath",
  "booleanOperation": -1,
  "clippingMaskMode": 0,
  "do_objectID": "E7BE322C-0752-4D08-AEA4-0450B73120F2",
  "edited": true,
  "exportOptions": {
    "_class": "exportOptions",
    "do_objectID": "D4040E03-2AFE-4FC5-9F71-EAC7E9CAE886",
    "exportFormats": [
    ],
    "includedLayerIds": [
    ],
    "layerOptions": 0,
    "shouldTrim": false
  },
  "frame": {
    "_class": "rect",
    "constrainProportions": false,
    "do_objectID": "5A3E998C-D6A8-42EE-8569-CA4F1C07C319",
    "height": 87.45734903796021,
    "width": 44.62580584416514,
    "x": 1070.51909663872,
    "y": 16.02912621359246
  },
  "hasClippingMask": false,
  "isClosed": true,
  "isFixedToViewport": false,
  "isFlippedHorizontal": false,
  "isFlippedVertical": false,
  "isLocked": false,
  "isVisible": true,
  "layerListExpandedType": 0,
  "name": "Path 10",
  "nameIsFixed": false,
  "pointRadiusBehaviour": 1,
  "points": [
    {
      "_class": "curvePoint",
      "cornerRadius": 0,
      "curveFrom": "{0, 0.15855711283021837}",
      "curveMode": 1,
      "curveTo": "{0, 0.15855711283021837}",
      "hasCurveFrom": false,
      "hasCurveTo": false,
      "point": "{0, 0.15855711283021837}"
    },
    {
      "_class": "curvePoint",
      "cornerRadius": 0,
      "curveFrom": "{0.1801680039691364, 0}",
      "curveMode": 1,
      "curveTo": "{0.1801680039691364, 0}",
      "hasCurveFrom": false,
      "hasCurveTo": false,
      "point": "{0.1801680039691364, 0}"
    },
    {
      "_class": "curvePoint",
      "cornerRadius": 0,
      "curveFrom": "{0.99999999999999922, 0.72731316338010998}",
      "curveMode": 1,
      "curveTo": "{0.99999999999999922, 0.72731316338010998}",
      "hasCurveFrom": false,
      "hasCurveTo": false,
      "point": "{0.99999999999999922, 0.72731316338010998}"
    },
    {
      "_class": "curvePoint",
      "cornerRadius": 0,
      "curveFrom": "{0.52707395938478341, 1.0000000000000004}",
      "curveMode": 1,
      "curveTo": "{0.52707395938478341, 1.0000000000000004}",
      "hasCurveFrom": false,
      "hasCurveTo": false,
      "point": "{0.52707395938478341, 1.0000000000000004}"
    },
    {
      "_class": "curvePoint",
      "cornerRadius": 0,
      "curveFrom": "{0.12805597851191586, 1.0000000000000002}",
      "curveMode": 1,
      "curveTo": "{0.12805597851191586, 1.0000000000000002}",
      "hasCurveFrom": false,
      "hasCurveTo": false,
      "point": "{0.12805597851191586, 1.0000000000000002}"
    },
    {
      "_class": "curvePoint",
      "cornerRadius": 0,
      "curveFrom": "{0.61699543207130714, 0.71329769141541466}",
      "curveMode": 1,
      "curveTo": "{0.61699543207130714, 0.71329769141541466}",
      "hasCurveFrom": false,
      "hasCurveTo": false,
      "point": "{0.61699543207130714, 0.71329769141541466}"
    }
  ],
  "resizingConstraint": 63,
  "resizingType": 0,
  "rotation": 0,
  "shouldBreakMaskChain": false,
  "style": {
    "_class": "style",
    "blur": {
      "_class": "blur",
      "center": "{0.5, 0.5}",
      "do_objectID": "A26AB70A-8810-48D1-967F-090ABC96E01B",
      "isEnabled": false,
      "motionAngle": 0,
      "radius": 9.221941801385682,
      "saturation": 1,
      "type": 0
    },
    "borders": [
      {
        "_class": "border",
        "color": {
          "_class": "color",
          "alpha": 1,
          "blue": 0.5920650959014893,
          "green": 0.5919613242149353,
          "red": 0.5920420289039612
        },
        "fillType": 0,
        "isEnabled": false,
        "position": 0,
        "thickness": 1.235
      }
    ],
    "do_objectID": "CC68E371-F2AF-4183-A5B2-25E948B3B925",
    "endMarkerType": 0,
    "fills": [
      {
        "_class": "fill",
        "color": {
          "_class": "color",
          "alpha": 1,
          "blue": 1,
          "green": 0.9999368786811829,
          "red": 1
        },
        "fillType": 0,
        "isEnabled": true,
        "noiseIndex": 0,
        "noiseIntensity": 0,
        "patternFillType": 1,
        "patternTileScale": 1
      }
    ],
    "miterLimit": 10,
    "startMarkerType": 0,
    "windingRule": 0
  },
  "userInfo": {
    "com.animaapp.stc-sketch-plugin": {
      "kModelPropertiesKey": {
      }
    }
  }
}