{
  "_class": "group",
  "booleanOperation": -1,
  "clippingMaskMode": 0,
  "do_objectID": "3896A7BD-D725-4628-AAE2-E4B7354C8F68",
  "exportOptions": {
    "_class": "exportOptions",
    "do_objectID": "65678638-4647-4086-9331-038B5C72573D",
    "exportFormats": [
    ],
    "includedLayerIds": [
    ],
    "layerOptions": 0,
    "shouldTrim": false
  },
  "frame": {
    "_class": "rect",
    "constrainProportions": false,
    "do_objectID": "F4D683C3-2B08-4944-B925-1CF30829721F",
    "height": 24,
    "width": 24,
    "x": 0,
    "y": 0
  },
  "hasClickThrough": false,
  "hasClippingMask": false,
  "isFixedToViewport": false,
  "isFlippedHorizontal": false,
  "isFlippedVertical": false,
  "isLocked": false,
  "isVisible": true,
  "layerListExpandedType": 0,
  "layers": [
    {
      "class": "shapeGroup",
      "id": "7115E254-89BF-4E4D-A381-CD1D524AB57F"
    }
  ],
  "name": "0: Icons / Dark / Star",
  "nameIsFixed": false,
  "resizingConstraint": 63,
  "resizingType": 0,
  "rotation": 0,
  "sharedStyleID": "8B8458CB-D9EB-4F9F-8B40-938357A63167",
  "shouldBreakMaskChain": false,
  "style": {
    "_class": "style",
    "do_objectID": "37E4956B-0455-4095-B559-DC6C2024BDF7",
    "endMarkerType": 0,
    "fills": [
      {
        "_class": "fill",
        "color": {
          "_class": "color",
          "alpha": 1,
          "blue": 0.8235294117647058,
          "green": 0.2705882352941176,
          "red": 0.3137254901960782
        },
        "fillType": 0,
        "isEnabled": true,
        "noiseIndex": 0,
        "noiseIntensity": 0,
        "patternFillType": 0,
        "patternTileScale": 1
      }
    ],
    "miterLimit": 10,
    "startMarkerType": 0,
    "windingRule": 1
  },
  "userInfo": {
    "com.animaapp.stc-sketch-plugin": {
      "kModelPropertiesKey": {
      }
    }
  }
}